montecarlo_swe/__init__.py
montecarlo_swe/cli.py
montecarlo_swe/config.py
montecarlo_swe/data_loader.py
montecarlo_swe/metrics.py
montecarlo_swe/output.py
montecarlo_swe/simulation.py
montecarlo_swe_probability-0.1.0.dist-info/METADATA
montecarlo_swe_probability-0.1.0.dist-info/WHEEL
montecarlo_swe_probability-0.1.0.dist-info/entry_points.txt
montecarlo_swe_probability-0.1.0.dist-info/licenses/LICENSE
montecarlo_swe_probability-0.1.0.dist-info/RECORD
