Metadata-Version: 2.4
Name: montecarlo-swe-probability
Version: 0.1.0
Summary: Monte Carlo simulation CLI for software engineering team forecasting
Project-URL: Homepage, https://github.com/TheLostByGass/montecarlo-swe-probability
Project-URL: Repository, https://github.com/TheLostByGass/montecarlo-swe-probability
Project-URL: Issues, https://github.com/TheLostByGass/montecarlo-swe-probability/issues
Author-email: TheLostByGass <info@revobill.de>
License-Expression: MIT
License-File: LICENSE
Keywords: agile,forecasting,monte-carlo,software-engineering,throughput
Classifier: Development Status :: 3 - Alpha
Classifier: Environment :: Console
Classifier: Intended Audience :: Developers
Classifier: License :: OSI Approved :: MIT License
Classifier: Operating System :: OS Independent
Classifier: Programming Language :: Python :: 3
Classifier: Programming Language :: Python :: 3.11
Classifier: Programming Language :: Python :: 3.12
Classifier: Programming Language :: Python :: 3.13
Classifier: Topic :: Software Development :: Quality Assurance
Requires-Python: >=3.11
Requires-Dist: click>=8.0
Requires-Dist: numpy>=1.24
Provides-Extra: dev
Requires-Dist: pytest-cov>=4.0; extra == 'dev'
Requires-Dist: pytest>=7.0; extra == 'dev'
